sencyberApps/__init__.py
sencyberApps/demo.py
sencyberApps/geometry.py
sencyberApps/quanternion.py
sencyberApps/tools.py
sencyberApps/io/__init__.py
sencyberApps/io/connection.py
sencyberApps/io/geo.py
sencyberApps/io/registClass.py
sencyber_tools-0.2.3.dist-info/LICENSE
sencyber_tools-0.2.3.dist-info/METADATA
sencyber_tools-0.2.3.dist-info/WHEEL
sencyber_tools-0.2.3.dist-info/top_level.txt
sencyber_tools-0.2.3.dist-info/RECORD
