Metadata-Version: 2.1
Name: sencyber-tools
Version: 0.2.3
Summary: Sencyber Tools
Home-page: https://github.com/Ag-elf/sencyber-tools
Author: shigure_hotaru
Author-email: lrscct@gmail.com
License: UNKNOWN
Project-URL: Bug Tracker, https://github.com/Ag-elf/sencyber-tools/issues
Platform: UNKNOWN
Classifier: Programming Language :: Python :: 3
Classifier: License :: OSI Approved :: MIT License
Classifier: Operating System :: OS Independent
Requires-Python: >=3.8
License-File: LICENSE
Requires-Dist: oss2
Requires-Dist: mysql-connector-python
Requires-Dist: cassandra-driver
